{
	"dialogue": [
		{
			"sound": "",
			"speed": 0.05,
			"portrait": "boii",
			"boxState": "normal",
			"expression": "talk",
			"text": "ah yes, we finaly have an imaginary boxin ring"
		},
		{
			"sound": "",
			"speed": 0.05,
			"portrait": "woofy",
			"boxState": "normal",
			"expression": "talk",
			"text": "bark bark (that's nice)"
		},
		{
			"sound": "",
			"speed": 0.05,
			"portrait": "woofy",
			"boxState": "normal",
			"expression": "talk",
			"text": "bark burk (look, it\"s boyfriend again!)"
		},
		{
			"sound": "",
			"speed": 0.05,
			"portrait": "bf",
			"boxState": "normal",
			"expression": "talk",
			"text": "let's rap"
		},
		{
			"sound": "",
			"speed": 0.05,
			"portrait": "boii",
			"boxState": "normal",
			"expression": "talk",
			"text": "fffffffffffffffffffffffffffineeeeeeeeeeeee"
		}
	]
}